runner.py
setup.py
vsut/__init__.py
vsut/assertion.py
vsut/format.py
vsut/unit.py
vsut.egg-info/PKG-INFO
vsut.egg-info/SOURCES.txt
vsut.egg-info/dependency_links.txt
vsut.egg-info/entry_points.txt
vsut.egg-info/top_level.txt