Metadata-Version: 1.1
Name: vsut
Version: 1.6
Summary: A simple unit testing framework for Python 3.4
Home-page: http://github.com/zillolo/vsut-python
Author: Alex Egger
Author-email: alex.egger96@gmail.com
License: MIT
Keywords: unit unittest test testing
Platform: UNKNOWN
Classifier: Development Status :: 4 - Beta
Classifier: Environment :: Console
Classifier: Intended Audience :: Developers
Classifier: License :: OSI Approved :: MIT License
Classifier: Programming Language :: Python :: 3
Classifier: Topic :: Software Development :: Testing
